medclip/__init__.py
medclip/constants.py
medclip/dataset.py
medclip/evaluator.py
medclip/losses.py
medclip/modeling_medclip.py
medclip/prompts.py
medclip/trainer.py
medclip/utils.py
medclip/vision_model.py
MedCLIP-0.0.3.dist-info/METADATA
MedCLIP-0.0.3.dist-info/WHEEL
MedCLIP-0.0.3.dist-info/top_level.txt
MedCLIP-0.0.3.dist-info/RECORD
