Metadata-Version: 2.1
Name: MedCLIP
Version: 0.0.3
Summary: Contrastive Learning from Medical Images and Text.
Home-page: https://github.com/RyanWangZf/MedCLIP
Author: Zifeng Wang
Author-email: zifengw2@illinois.edu
License: UNKNOWN
Keywords: vision-language model,X-ray,deep learning,AI,healthcare
Platform: UNKNOWN
Classifier: Programming Language :: Python :: 3
Classifier: Programming Language :: Python :: 3.8
Classifier: Programming Language :: Python :: 3.9
Classifier: License :: OSI Approved :: BSD License
Classifier: Operating System :: OS Independent
